beit/__init__.py
beit/runfiles.py
beit/qubo_solver/__init__.py
beit/qubo_solver/architecture.py
beit/qubo_solver/beit_solver.py
beit/qubo_solver/endpoint.py
beit/qubo_solver/qubo_instance.py
beit/qubo_solver/solver_connection.py
beit/qubo_solver/schemas/__init__.py
beit/qubo_solver/schemas/result.json
beit/qubo_solver/schemas/result_response.json
beit/qubo_solver/schemas/solve.json
beit/qubo_solver/schemas/solve_response.json
beit_qubo_solver-0.2.0.dist-info/METADATA
beit_qubo_solver-0.2.0.dist-info/WHEEL
beit_qubo_solver-0.2.0.dist-info/top_level.txt
beit_qubo_solver-0.2.0.dist-info/RECORD
